[
    {
        "id": 1,
        "name": "Adventurer",
        "element": "Metal",
        "equippable": "Sword,Mace,Dagger,Axe,Ring,Necklace,Staff,Belt,Earring,Bracer,Pet,Scythe",
        "swf": "class-adventurer.swf",
        "savable": 0,
        "armorId": 9800005,
        "weaponId": 9800004
    },
    {
        "id": 2,
        "name": "Warrior",
        "element": "Metal",
        "equippable": "Sword,Mace,Dagger,Axe,Ring,Necklace,Staff,Belt,Earring,Bracer,Pet,Cape,Wings,Helmet,Armor,Wand,Scythe,Trinket,Artifact",
        "swf": "class-2016warrior-r3.swf?ver=1",
        "savable": 2,
        "armorId": 9800009,
        "weaponId": 9800008
    },
    {
        "id": 3,
        "name": "Mage",
        "element": "Nature",
        "equippable": "Sword,Mace,Dagger,Axe,Ring,Necklace,Staff,Belt,Earring,Bracer,Pet,Helmet,Cape,Wings,Helmet,Armor,Wand,Scythe,Trinket,Artifact",
        "swf": "class-2016mage-r3.swf?ver=1",
        "savable": 2,
        "armorId": 9800013,
        "weaponId": 9800012
    },
    {
        "id": 4,
        "name": "Rogue",
        "element": "Metal",
        "equippable": "Sword,Mace,Dagger,Axe,Ring,Necklace,Staff,Belt,Earring,Bracer,Pet,Cape,Wings,Helmet,Armor,Wand,Scythe,Trinket,Artifact",
        "swf": "class-2016rogue-r5.swf?ver=2",
        "savable": 2,
        "armorId": 9800017,
        "weaponId": 9800016
    },
    {
        "id": 7,
        "name": "Guardian",
        "element": "Metal",
        "equippable": "Sword,Mace,Dagger,Axe,Ring,Necklace,Staff,Belt,Earring,Bracer,Pet,Cape,Wings,Helmet,Armor,Wand,Scythe,Trinket,Artifact",
        "swf": "class-GuardianRevamp-r6.swf",
        "savable": 1,
        "armorId": 9800029,
        "weaponId": 9800028
    },
    {
        "id": 8,
        "name": "ChickencowLord",
        "element": "Stone",
        "equippable": "Sword,Mace,Dagger,Axe,Ring,Necklace,Staff,Belt,Earring,Bracer,Pet,Cape,Wings,Helmet,Armor,Wand,Scythe,Trinket,Artifact",
        "swf": "class-chickencow-r3.swf",
        "savable": 2,
        "armorId": 9800033,
        "weaponId": 9800032
    },
    {
        "id": 12,
        "name": "DragonLord",
        "element": "Metal",
        "equippable": "Sword,Mace,Dagger,Axe,Ring,Necklace,Staff,Belt,Earring,Bracer,Pet,Cape,Wings,Helmet,Armor,Wand,Scythe,Trinket,Artifact",
        "swf": "class-dragonlord35.swf?ver=7",
        "savable": 2,
        "armorId": 9800049,
        "weaponId": 9800048
    },
    {
        "id": 13,
        "name": "DragonRider",
        "element": "None",
        "equippable": "",
        "swf": "class-dragonrider-NEWr4.swf?ver=1",
        "savable": 0,
        "armorId": 9800053,
        "weaponId": 9800052
    },
    {
        "id": 14,
        "name": "DeathKnight",
        "element": "Darkness",
        "equippable": "Sword,Mace,Dagger,Axe,Ring,Necklace,Staff,Belt,Earring,Bracer,Pet,Cape,Wings,Helmet,Armor,Wand,Scythe,Trinket,Artifact",
        "swf": "class-DeathKnightRevamp-r28.swf?ver=3",
        "savable": 2,
        "armorId": 9800057,
        "weaponId": 9800056
    },
    {
        "id": 15,
        "name": "Pirate",
        "element": "Darkness",
        "equippable": "Sword,Mace,Dagger,Axe,Ring,Necklace,Staff,Belt,Earring,Bracer,Pet,Cape,Wings,Helmet,Armor,Wand,Scythe,Trinket,Artifact",
        "swf": "class-PirateRevamp-r2.swf?ver=4",
        "savable": 2,
        "armorId": 9800061,
        "weaponId": 9800060
    },
    {
        "id": 16,
        "name": "Pirate",
        "element": "Darkness",
        "equippable": "Sword,Mace,Dagger,Axe,Ring,Necklace,Staff,Belt,Earring,Bracer,Pet,Cape,Wings,Helmet,Armor,Wand,Scythe,Trinket,Artifact",
        "swf": "class-PirateRevamp-r2.swf?ver=4",
        "savable": 2,
        "armorId": 9800065,
        "weaponId": 9800064
    },
    {
        "id": 20,
        "name": "Ninja",
        "element": "Darkness",
        "equippable": "Sword,Mace,Dagger,Axe,Ring,Necklace,Staff,Belt,Earring,Bracer,Pet,Cape,Wings,Helmet,Armor,Wand,Scythe,Trinket,Artifact",
        "swf": "class-NinjaRevamp2023.swf?ver=6",
        "savable": 2,
        "armorId": 9800081,
        "weaponId": 9800080
    },
    {
        "id": 21,
        "name": "PumpkinLord",
        "element": "Darkness",
        "equippable": "Sword,Mace,Dagger,Axe,Ring,Necklace,Staff,Belt,Earring,Bracer,Pet,Cape,Wings,Helmet,Armor,Wand,Scythe,Trinket,Artifact",
        "swf": "class-PumpkinRevamp.swf?ver=2",
        "savable": 2,
        "armorId": 9800085,
        "weaponId": 9800084
    },
    {
        "id": 22,
        "name": "Ranger",
        "element": "Metal",
        "equippable": "Sword,Mace,Dagger,Axe,Ring,Necklace,Staff,Belt,Earring,Bracer,Pet,Cape,Wings,Helmet,Armor,Wand,Scythe,Trinket,Artifact",
        "swf": "class-rangerRevamp-r9.swf?ver=3",
        "savable": 2,
        "armorId": 9800089,
        "weaponId": 9800088
    },
    {
        "id": 23,
        "name": "Snuggle Bear",
        "element": "Metal",
        "equippable": "Sword,Mace,Dagger,Axe,Ring,Necklace,Staff,Belt,Earring,Bracer,Pet,Cape,Wings,Helmet,Armor,Wand,Scythe,Trinket,Artifact",
        "swf": "class-snugglebear-r1.swf",
        "savable": 2,
        "armorId": 9800093,
        "weaponId": 9800092
    },
    {
        "id": 24,
        "name": "Paladin",
        "element": "Metal",
        "equippable": "Sword,Mace,Dagger,Axe,Ring,Necklace,Staff,Belt,Earring,Bracer,Pet,Cape,Wings,Helmet,Armor,Wand,Scythe,Trinket,Artifact",
        "swf": "class-PallyRevamp2023.swf?ver=4",
        "savable": 2,
        "armorId": 9800097,
        "weaponId": 9800096
    },
    {
        "id": 25,
        "name": "Kid Artix",
        "element": "None",
        "equippable": "",
        "swf": "class-artixkid.swf",
        "savable": 0,
        "armorId": 9800101,
        "weaponId": 9800100
    },
    {
        "id": 26,
        "name": "DragonLord",
        "element": "Metal",
        "equippable": "Sword,Mace,Dagger,Axe,Ring,Necklace,Staff,Belt,Earring,Bracer,Pet,Cape,Wings,Helmet,Armor,Wand,Scythe,Trinket,Artifact",
        "swf": "class-dragonlord35.swf?ver=7",
        "savable": 2,
        "armorId": 9800105,
        "weaponId": 9800104
    },
    {
        "id": 27,
        "name": "DragonLord",
        "element": "Metal",
        "equippable": "Sword,Mace,Dagger,Axe,Ring,Necklace,Staff,Belt,Earring,Bracer,Pet,Cape,Wings,Helmet,Armor,Wand,Scythe,Trinket,Artifact",
        "swf": "class-dragonlord35.swf?ver=7",
        "savable": 2,
        "armorId": 9800109,
        "weaponId": 9800108
    },
    {
        "id": 28,
        "name": "Necromancer",
        "element": "Darkness",
        "equippable": "Sword,Mace,Dagger,Axe,Ring,Necklace,Staff,Belt,Earring,Bracer,Pet,Cape,Wings,Helmet,Armor,Wand,Scythe,Trinket,Artifact",
        "swf": "class-NecroRevamp-r10.swf?ver=1",
        "savable": 2,
        "armorId": 9800113,
        "weaponId": 9800112
    },
    {
        "id": 29,
        "name": "Pirate Monkey",
        "element": "Metal",
        "equippable": "Sword,Mace,Dagger,Axe,Ring,Necklace,Staff,Belt,Earring,Bracer,Pet,Cape,Wings,Armor,Wand,Scythe,Trinket,Artifact",
        "swf": "class-monkeypirate2r2.swf",
        "savable": 2,
        "armorId": 9800117,
        "weaponId": 9800116
    },
    {
        "id": 30,
        "name": "Ninja Monkey",
        "element": "Metal",
        "equippable": "Sword,Mace,Dagger,Axe,Ring,Necklace,Staff,Belt,Earring,Bracer,Pet,Cape,Wings,Armor,Wand,Scythe,Trinket,Artifact",
        "swf": "class-MonkeyNinja2r3.swf?ver=1",
        "savable": 2,
        "armorId": 9800121,
        "weaponId": 9800120
    },
    {
        "id": 31,
        "name": "Ancient Shadow Warrior",
        "element": "Metal",
        "equippable": "Sword,Mace,Dagger,Axe,Ring,Necklace,Staff,Belt,Earring,Bracer,Pet,Cape,Wings,Helmet,Armor,Wand,Scythe,Trinket,Artifact",
        "swf": "class-tshirtwarrior-r2.swf?ver=2",
        "savable": 2,
        "armorId": 9800125,
        "weaponId": 9800124
    },
    {
        "id": 32,
        "name": "Ancient Shadow Mage",
        "element": "Nature",
        "equippable": "Sword,Mace,Dagger,Axe,Ring,Necklace,Staff,Belt,Earring,Bracer,Pet,Helmet,Cape,Wings,Helmet,Armor,Wand,Scythe,Trinket,Artifact",
        "swf": "class-tshirtmage-r2.swf?ver=1",
        "savable": 2,
        "armorId": 9800129,
        "weaponId": 9800128
    },
    {
        "id": 33,
        "name": "Ancient Shadow Rogue",
        "element": "Metal",
        "equippable": "Sword,Mace,Dagger,Axe,Ring,Necklace,Staff,Belt,Earring,Bracer,Pet,Cape,Wings,Helmet,Armor,Wand,Scythe,Trinket,Artifact",
        "swf": "class-tshirtrogue-r6.swf",
        "savable": 2,
        "armorId": 9800133,
        "weaponId": 9800132
    },
    {
        "id": 34,
        "name": "Kid Nythera",
        "element": "Energy",
        "equippable": "",
        "swf": "class-nytheraKID.swf",
        "savable": 0,
        "armorId": 9800137,
        "weaponId": 9800136
    },
    {
        "id": 35,
        "name": "Kid Nythera",
        "element": "Energy",
        "equippable": "",
        "swf": "class-nytheraKID2.swf",
        "savable": 0,
        "armorId": 9800141,
        "weaponId": 9800140
    },
    {
        "id": 36,
        "name": "Evolved PumpkinLord",
        "element": "Darkness",
        "equippable": "Sword,Mace,Dagger,Axe,Ring,Necklace,Staff,Belt,Earring,Bracer,Pet,Cape,Wings,Helmet,Armor,Wand,Scythe,Trinket,Artifact",
        "swf": "class-PumpkinEvoRevamp-r2.swf",
        "savable": 2,
        "armorId": 9800145,
        "weaponId": 9800144
    },
    {
        "id": 37,
        "name": "DragonSlayer",
        "element": "Metal",
        "equippable": "Sword,Mace,Dagger,Axe,Ring,Necklace,Staff,Belt,Earring,Bracer,Pet,Cape,Wings,Helmet,Armor,Wand,Scythe,Trinket,Artifact",
        "swf": "class-DragonslayerRevamp-r5.swf",
        "savable": 2,
        "armorId": 9800149,
        "weaponId": 9800148
    },
    {
        "id": 38,
        "name": "Frost Moglin",
        "element": "Nature",
        "equippable": "Sword,Mace,Dagger,Axe,Ring,Necklace,Staff,Belt,Earring,Bracer,Pet,Cape,Wings,Helmet,Armor,Wand,Scythe,Trinket,Artifact",
        "swf": "class-FrostMogRevamp-r3.swf?ver=1",
        "savable": 2,
        "armorId": 9800153,
        "weaponId": 9800152
    },
    {
        "id": 39,
        "name": "Nythera",
        "element": "Evil",
        "equippable": "",
        "swf": "class-Nythera.swf",
        "savable": 0,
        "armorId": 9800157,
        "weaponId": 9800156
    },
    {
        "id": 40,
        "name": "Warlic",
        "element": "Good",
        "equippable": "",
        "swf": "class-Warlic.swf",
        "savable": 0,
        "armorId": 9800161,
        "weaponId": 9800160
    },
    {
        "id": 42,
        "name": "Boy Wonder",
        "element": "Metal",
        "equippable": "Sword,Mace,Dagger,Axe,Ring,Necklace,Staff,Belt,Earring,Bracer,Pet,Cape,Wings,Helmet,Armor,Wand,Scythe,Trinket",
        "swf": "class-ashr3.swf",
        "savable": 2,
        "armorId": 9800169,
        "weaponId": 9800168
    },
    {
        "id": 43,
        "name": "Angler",
        "element": "None",
        "equippable": "",
        "swf": "class-angler-r1.swf",
        "savable": 0,
        "armorId": 9800173,
        "weaponId": 9800172
    },
    {
        "id": 44,
        "name": "Evolved Chickencow",
        "element": "Stone",
        "equippable": "Sword,Mace,Dagger,Axe,Ring,Necklace,Staff,Belt,Earring,Bracer,Pet,Cape,Wings,Helmet,Armor,Wand,Scythe,Trinket,Artifact",
        "swf": "class-chickencow-evolved-r5.swf?ver=1",
        "savable": 2,
        "armorId": 9800177,
        "weaponId": 9800176
    },
    {
        "id": 45,
        "name": "Young Hero",
        "element": "Metal",
        "equippable": "Sword,Mace,Dagger,Axe,Ring,Necklace,Staff,Belt,Earring,Bracer,Pet,Cape,Wings,Helmet,Armor,Wand,Scythe,Trinket",
        "swf": "class-ash-2r5.swf",
        "savable": 1,
        "armorId": 9800181,
        "weaponId": 9800180
    },
    {
        "id": 46,
        "name": "Technomancer",
        "element": "Light",
        "equippable": "Sword,Mace,Dagger,Axe,Ring,Necklace,Staff,Belt,Earring,Bracer,Pet,Cape,Wings,Helmet,Armor,Wand,Scythe,Trinket,Artifact",
        "swf": "class-TechnoRevamp-r10.swf?ver=3",
        "savable": 2,
        "armorId": 9800185,
        "weaponId": 9800184
    },
    {
        "id": 47,
        "name": "GPS 2.0",
        "element": "Metal",
        "equippable": "Sword,Mace,Dagger,Axe,Ring,Necklace,Staff,Belt,Earring,Bracer,Pet,Cape,Wings,Helmet,Armor,Wand,Scythe,Trinket,Artifact",
        "swf": "GPSr2-r2.swf",
        "savable": 2791,
        "armorId": 9800187,
        "weaponId": 9800186
    },
    {
        "id": 49,
        "name": "Xan",
        "element": "Fire",
        "equippable": "",
        "swf": "class-xannew.swf ",
        "savable": 0,
        "armorId": 9800197,
        "weaponId": 9800196
    },
    {
        "id": 50,
        "name": "DragonRider",
        "element": "None",
        "equippable": "",
        "swf": "class-dragonrider-NEWr4.swf?ver=1",
        "savable": 0,
        "armorId": 9800201,
        "weaponId": 9800200
    },
    {
        "id": 51,
        "name": "Test",
        "element": "???",
        "equippable": "Sword,Mace,Dagger,Axe,Ring,Necklace,Staff,Belt,Earring,Bracer,Pet,Cape,Wings,Helmet,Armor,Wand,Scythe,Trinket,Artifact",
        "swf": "class-shadowhunter-revamp.swf",
        "savable": 0,
        "armorId": 9800205,
        "weaponId": 9800204
    },
    {
        "id": 52,
        "name": "DragonWarrior",
        "element": "Metal",
        "equippable": "Sword,Mace,Dagger,Axe,Ring,Necklace,Staff,Belt,Earring,Bracer,Pet,Cape,Wings,Helmet,Armor,Wand,Scythe,Trinket,Artifact",
        "swf": "class-dragonwarrior_revamp-r3.swf",
        "savable": 2,
        "armorId": 9800209,
        "weaponId": 9800208
    },
    {
        "id": 53,
        "name": "DragonMage",
        "element": "Nature",
        "equippable": "Sword,Mace,Dagger,Axe,Ring,Necklace,Staff,Belt,Earring,Bracer,Pet,Helmet,Cape,Wings,Helmet,Armor,Wand,Scythe,Trinket,Artifact",
        "swf": "class-dragonmage_revamp-r5.swf?ver=1",
        "savable": 2,
        "armorId": 9800213,
        "weaponId": 9800212
    },
    {
        "id": 54,
        "name": "DragonRogue",
        "element": "Metal",
        "equippable": "Sword,Mace,Dagger,Axe,Ring,Necklace,Staff,Belt,Earring,Bracer,Pet,Cape,Wings,Helmet,Armor,Wand,Scythe,Trinket,Artifact",
        "swf": "class-dragonrogue_revamp-r1.swf?ver=2",
        "savable": 2,
        "armorId": 9800217,
        "weaponId": 9800216
    },
    {
        "id": 55,
        "name": "Knight Lite",
        "element": "Metal",
        "equippable": "Sword,Mace,Dagger,Axe,Ring,Necklace,Staff,Belt,Earring,Bracer,Pet,Helmet,Cape,Wings,Helmet,Armor,Wand,Scythe,Trinket",
        "swf": "class-Ash-LightKnightr2.swf",
        "savable": 2,
        "armorId": 9800221,
        "weaponId": 9800220
    },
    {
        "id": 56,
        "name": "Davey",
        "element": "Metal",
        "equippable": "",
        "swf": "class-davey.swf",
        "savable": 0,
        "armorId": 9800225,
        "weaponId": 9800224
    },
    {
        "id": 57,
        "name": "Kathool Adept",
        "element": "Darkness",
        "equippable": "Sword,Mace,Dagger,Axe,Ring,Necklace,Staff,Belt,Earring,Bracer,Pet,Helmet,Cape,Wings,Helmet,Armor,Wand,Scythe,Trinket,Artifact",
        "swf": "class-adept-r7.swf",
        "savable": 3825,
        "armorId": 9800227,
        "weaponId": 9800226
    },
    {
        "id": 58,
        "name": "Elemental Nythera",
        "element": "Darkness",
        "equippable": "",
        "swf": "class-nytheranew-r2.swf",
        "savable": 0,
        "armorId": 9800233,
        "weaponId": 9800232
    },
    {
        "id": 60,
        "name": "DragonLord",
        "element": "Metal",
        "equippable": "Sword,Mace,Dagger,Axe,Ring,Necklace,Staff,Belt,Earring,Bracer,Pet,Cape,Wings,Helmet,Armor,Wand,Scythe,Trinket,Artifact",
        "swf": "class-dragonlord35.swf?ver=7",
        "savable": 2,
        "armorId": 9800241,
        "weaponId": 9800240
    },
    {
        "id": 62,
        "name": "Nythera",
        "element": "Darkness",
        "equippable": "",
        "swf": "class-nytheranew2.swf",
        "savable": 0,
        "armorId": 9800249,
        "weaponId": 9800248
    },
    {
        "id": 63,
        "name": "Young Vilmor",
        "element": "Metal",
        "equippable": "",
        "swf": "class-vilmor.swf",
        "savable": 0,
        "armorId": 9800253,
        "weaponId": 9800252
    },
    {
        "id": 64,
        "name": "Zardbie",
        "element": "Nature",
        "equippable": "Sword,Mace,Dagger,Axe,Ring,Necklace,Staff,Belt,Earring,Bracer,Pet,Cape,Wings,Helmet,Armor,Wand,Scythe,Trinket,Artifact",
        "swf": "class-zardbieRebrained-r2.swf",
        "savable": 2,
        "armorId": 9800257,
        "weaponId": 9800256
    },
    {
        "id": 67,
        "name": "SoulWeaver",
        "element": "Metal",
        "equippable": "Sword,Mace,Dagger,Axe,Ring,Necklace,Staff,Belt,Earring,Bracer,Pet,Cape,Wings,Helmet,Armor,Wand,Scythe,Trinket,Artifact",
        "swf": "class-soul2024-r1.swf",
        "savable": 2,
        "armorId": 9800269,
        "weaponId": 9800268
    },
    {
        "id": 68,
        "name": "En",
        "element": "Darkness",
        "equippable": "",
        "swf": "class-en.swf",
        "savable": 0,
        "armorId": 9800273,
        "weaponId": 9800272
    },
    {
        "id": 69,
        "name": "Fae",
        "element": "Nature",
        "equippable": "",
        "swf": "class-faeYEAH.swf",
        "savable": 0,
        "armorId": 9800277,
        "weaponId": 9800276
    },
    {
        "id": 70,
        "name": "Entropy",
        "element": "Darkness",
        "equippable": "Sword,Mace,Dagger,Axe,Ring,Necklace,Staff,Belt,Earring,Bracer,Pet,Cape,Wings,Helmet,Armor,Wand,Scythe,Trinket,Artifact",
        "swf": "class-entropy-r21.swf",
        "savable": 5997,
        "armorId": 9800279,
        "weaponId": 9800278
    },
    {
        "id": 71,
        "name": "Alexander",
        "element": "Ice",
        "equippable": "Sword,Mace,Dagger,Axe,Ring,Necklace,Staff,Belt,Earring,Bracer,Pet,Cape,Wings,Helmet,Armor,Wand,Scythe,Trinket",
        "swf": "class-youngxan-r4.swf",
        "savable": 0,
        "armorId": 9800285,
        "weaponId": 9800284
    },
    {
        "id": 72,
        "name": "Togslayer",
        "element": "Ice",
        "equippable": "Sword,Mace,Dagger,Axe,Ring,Necklace,Staff,Belt,Earring,Bracer,Pet,Cape,Wings,Helmet,Armor,Wand,Scythe,Trinket,Artifact",
        "swf": "class-Togslayerr8.swf?ver=1",
        "savable": 2,
        "armorId": 9800289,
        "weaponId": 9800288
    },
    {
        "id": 74,
        "name": "Ascendant",
        "element": "Ice",
        "equippable": "Sword,Mace,Dagger,Axe,Ring,Necklace,Staff,Belt,Earring,Bracer,Pet,Cape,Wings,Helmet,Armor,Wand,Scythe,Trinket,Artifact",
        "swf": "class-ascendant-NEW.swf?ver=1",
        "savable": 2,
        "armorId": 9800297,
        "weaponId": 9800296
    },
    {
        "id": 75,
        "name": "Riftwalker",
        "element": "Ice",
        "equippable": "Sword,Mace,Dagger,Axe,Ring,Necklace,Staff,Belt,Earring,Bracer,Pet,Cape,Wings,Helmet,Armor,Wand,Scythe,Trinket,Artifact",
        "swf": "CLASS-Riftwalker-NEW.swf",
        "savable": 2,
        "armorId": 9800301,
        "weaponId": 9800300
    },
    {
        "id": 76,
        "name": "Cryptic",
        "element": "Ice",
        "equippable": "Sword,Mace,Dagger,Axe,Ring,Necklace,Staff,Belt,Earring,Bracer,Pet,Cape,Wings,Helmet,Armor,Wand,Scythe,Trinket,Artifact",
        "swf": "class-cryptic-NEW.swf",
        "savable": 2,
        "armorId": 9800305,
        "weaponId": 9800304
    },
    {
        "id": 77,
        "name": "Pyromancer",
        "element": "Fire",
        "equippable": "Sword,Mace,Dagger,Axe,Ring,Necklace,Staff,Belt,Earring,Bracer,Pet,Helmet,Cape,Wings,Helmet,Armor,Wand,Scythe,Trinket,Artifact",
        "swf": "class-pyromancer-r15.swf?ver=5",
        "savable": 7660,
        "armorId": 9800307,
        "weaponId": 9800306
    },
    {
        "id": 78,
        "name": "Cat",
        "element": "Darkness",
        "equippable": "",
        "swf": "class-catdeatharrows.swf",
        "savable": 0,
        "armorId": 9800313,
        "weaponId": 9800312
    },
    {
        "id": 79,
        "name": "SoulWeaver",
        "element": "Metal",
        "equippable": "Sword,Mace,Dagger,Axe,Ring,Necklace,Staff,Belt,Earring,Bracer,Pet,Cape,Wings,Helmet,Armor,Wand,Scythe,Trinket,Artifact",
        "swf": "class-soul2024-r1.swf",
        "savable": 2,
        "armorId": 9800317,
        "weaponId": 9800316
    },
    {
        "id": 81,
        "name": "Rolith Dress Uniform",
        "element": "Metal",
        "equippable": "",
        "swf": "class-Wedding Rolith-r2.swf",
        "savable": 0,
        "armorId": 9800325,
        "weaponId": 9800324
    },
    {
        "id": 82,
        "name": "Defensive Artix",
        "element": "Metal",
        "equippable": "",
        "swf": "class-Artix-BM.swf",
        "savable": 0,
        "armorId": 9800329,
        "weaponId": 9800328
    },
    {
        "id": 83,
        "name": "DragonRider",
        "element": "None",
        "equippable": "",
        "swf": "class-dragonrider-NEWr4.swf?ver=1",
        "savable": 0,
        "armorId": 9800333,
        "weaponId": 9800332
    },
    {
        "id": 84,
        "name": "ShadowHunter",
        "element": "Metal",
        "equippable": "Sword,Mace,Dagger,Axe,Ring,Necklace,Staff,Belt,Earring,Bracer,Pet,Cape,Wings,Helmet,Armor,Wand,Scythe,Trinket,Artifact",
        "swf": "class-shadowhunter-revamp.swf?ver=6",
        "savable": 2,
        "armorId": 9800337,
        "weaponId": 9800336
    },
    {
        "id": 85,
        "name": "Envy",
        "element": "Evil",
        "equippable": "",
        "swf": "class-envy.swf",
        "savable": 0,
        "armorId": 9800341,
        "weaponId": 9800340
    },
    {
        "id": 86,
        "name": "ChronoZ",
        "element": "Ice",
        "equippable": "Sword,Mace,Dagger,Axe,Ring,Necklace,Staff,Belt,Earring,Bracer,Pet,Cape,Wings,Helmet,Armor,Wand,Scythe,Trinket,Artifact",
        "swf": "class-ChronoZ-r8.swf?ver=3",
        "savable": 11730,
        "armorId": 9800343,
        "weaponId": 9800342
    },
    {
        "id": 87,
        "name": "Edd Disguise",
        "element": "Metal",
        "equippable": "",
        "swf": "class-Edd.swf",
        "savable": 0,
        "armorId": 9800349,
        "weaponId": 9800348
    },
    {
        "id": 88,
        "name": "Kara",
        "element": "Wind",
        "equippable": "Ring,Necklace,Belt,Earring,Bracer,Pet",
        "swf": "class-Eukara3.swf",
        "savable": 0,
        "armorId": 9800353,
        "weaponId": 9800352
    },
    {
        "id": 89,
        "name": "Edd Disguise",
        "element": "Metal",
        "equippable": "",
        "swf": "class-EddRe.swf",
        "savable": 0,
        "armorId": 9800357,
        "weaponId": 9800356
    },
    {
        "id": 90,
        "name": "Preview",
        "element": "???",
        "equippable": "Sword,Mace,Dagger,Axe,Ring,Necklace,Staff,Belt,Earring,Bracer,Pet,Cape,Wings,Helmet,Armor,Wand,Scythe,Trinket,Artifact",
        "swf": "class-caitiff.swf",
        "savable": 0,
        "armorId": 9800361,
        "weaponId": 9800360
    },
    {
        "id": 91,
        "name": "Icebound Revenant",
        "element": "Ice",
        "equippable": "Sword,Mace,Dagger,Axe,Ring,Necklace,Staff,Belt,Earring,Bracer,Pet,Cape,Wings,Helmet,Armor,Wand,Scythe,Trinket,Artifact",
        "swf": "class-IceboundRevenant-r3.swf",
        "savable": 12250,
        "armorId": 9800363,
        "weaponId": 9800362
    },
    {
        "id": 93,
        "name": "Vaal",
        "element": "Fire",
        "equippable": "",
        "swf": "class-Vaal.swf",
        "savable": 0,
        "armorId": 9800373,
        "weaponId": 9800372
    },
    {
        "id": 94,
        "name": "Synchronized",
        "element": "Good",
        "equippable": "",
        "swf": "class-TomixPandora.swf ",
        "savable": 0,
        "armorId": 9800377,
        "weaponId": 9800376
    },
    {
        "id": 95,
        "name": "Baby Dragon",
        "element": "None",
        "equippable": "",
        "swf": "class-DragonWarBaby-r2.swf ",
        "savable": 0,
        "armorId": 9800381,
        "weaponId": 9800380
    },
    {
        "id": 96,
        "name": "Toddler Dragon",
        "element": "None",
        "equippable": "",
        "swf": "class-DragonWarToddler-r2.swf ",
        "savable": 0,
        "armorId": 9800385,
        "weaponId": 9800384
    },
    {
        "id": 97,
        "name": "Kid Dragon",
        "element": "None",
        "equippable": "",
        "swf": "class-DragonWarKid-r3.swf?ver=1",
        "savable": 0,
        "armorId": 9800389,
        "weaponId": 9800388
    },
    {
        "id": 99,
        "name": "MageKnight",
        "element": "Light",
        "equippable": "",
        "swf": "class-Leon.swf ",
        "savable": 0,
        "armorId": 9800397,
        "weaponId": 9800396
    },
    {
        "id": 100,
        "name": "Kid Raven",
        "element": "Energy",
        "equippable": "",
        "swf": "class-RavenKID.swf ",
        "savable": 0,
        "armorId": 9800401,
        "weaponId": 9800400
    },
    {
        "id": 101,
        "name": "Ascended Chickencow",
        "element": "???",
        "equippable": "Sword,Mace,Dagger,Axe,Ring,Necklace,Staff,Belt,Earring,Bracer,Pet,Cape,Wings,Helmet,Armor,Wand,Scythe,Trinket,Artifact",
        "swf": "class-Chickencow-Ascend-r3.swf ",
        "savable": 2,
        "armorId": 9800405,
        "weaponId": 9800404
    },
    {
        "id": 102,
        "name": "Reuse",
        "element": "Ebil",
        "equippable": "Sword,Mace,Dagger,Axe,Ring,Necklace,Staff,Belt,Earring,Bracer,Pet,Cape,Wings,Helmet,Armor,Wand,Scythe,Trinket,Artifact",
        "swf": "class-AshJoke.swf",
        "savable": 0,
        "armorId": 9800409,
        "weaponId": 9800408
    },
    {
        "id": 103,
        "name": "Edd Disguise",
        "element": "Metal",
        "equippable": "",
        "swf": "class-EddFancyFull.swf",
        "savable": 0,
        "armorId": 9800413,
        "weaponId": 9800412
    },
    {
        "id": 104,
        "name": "Edd Disguise",
        "element": "Metal",
        "equippable": "",
        "swf": "class-EddFancyMin.swf",
        "savable": 0,
        "armorId": 9800417,
        "weaponId": 9800416
    },
    {
        "id": 105,
        "name": "Fleshweaver",
        "element": "Evil",
        "equippable": "",
        "swf": "class-Izboirr.swf",
        "savable": 0,
        "armorId": 9800421,
        "weaponId": 9800420
    },
    {
        "id": 106,
        "name": "Unbread",
        "element": "None",
        "equippable": "Sword,Mace,Dagger,Axe,Ring,Necklace,Staff,Belt,Earring,Bracer,Pet,Cape,Wings,Helmet,Armor,Wand,Scythe,Trinket,Artifact",
        "swf": "class-unbreadzardbie-r1.swf",
        "savable": 2,
        "armorId": 9800425,
        "weaponId": 9800424
    },
    {
        "id": 108,
        "name": "DoomKnight",
        "element": "Darkness",
        "equippable": "Sword,Mace,Dagger,Axe,Ring,Necklace,Staff,Belt,Earring,Bracer,Pet,Cape,Wings,Helmet,Armor,Wand,Scythe,Trinket,Artifact",
        "swf": "class-DoomKnightRevamp-r14.swf?ver=2",
        "savable": 14819,
        "armorId": 9800435,
        "weaponId": 9800434
    },
    {
        "id": 109,
        "name": "Beast Master",
        "element": "Nature",
        "equippable": "Sword,Mace,Dagger,Axe,Ring,Necklace,Staff,Belt,Earring,Bracer,Pet,Cape,Wings,Helmet,Armor,Wand,Scythe,Trinket,Artifact",
        "swf": "class-beastmaster.swf",
        "savable": 0,
        "armorId": 9800437,
        "weaponId": 9800436
    },
    {
        "id": 110,
        "name": "Shaman",
        "element": "Nature",
        "equippable": "Sword,Mace,Dagger,Axe,Ring,Necklace,Staff,Belt,Earring,Bracer,Pet,Cape,Wings,Helmet,Armor,Wand,Scythe,Trinket,Artifact",
        "swf": "class-shaman.swf",
        "savable": 0,
        "armorId": 9800441,
        "weaponId": 9800440
    },
    {
        "id": 111,
        "name": "Druid",
        "element": "Nature",
        "equippable": "Sword,Mace,Dagger,Axe,Ring,Necklace,Staff,Belt,Earring,Bracer,Pet,Cape,Wings,Helmet,Armor,Wand,Scythe,Trinket,Artifact",
        "swf": "class-druid.swf",
        "savable": 0,
        "armorId": 9800445,
        "weaponId": 9800444
    },
    {
        "id": 112,
        "name": "Chaosweaver",
        "element": "Metal",
        "equippable": "Sword,Mace,Dagger,Axe,Ring,Necklace,Staff,Belt,Earring,Bracer,Pet,Cape,Wings,Helmet,Armor,Wand,Scythe,Trinket,Artifact",
        "swf": "class-chaosweaver-r4.swf",
        "savable": 19072,
        "armorId": 9800447,
        "weaponId": 9800446
    },
    {
        "id": 113,
        "name": "Kid",
        "element": "Nature",
        "equippable": "",
        "swf": "class-KidHero.swf",
        "savable": 0,
        "armorId": 9800453,
        "weaponId": 9800452
    },
    {
        "id": 114,
        "name": "Bone Exoskeleton",
        "element": "Metal",
        "equippable": "",
        "swf": "class-Exoskeleton.swf",
        "savable": 0,
        "armorId": 9800457,
        "weaponId": 9800456
    },
    {
        "id": 115,
        "name": "Shadow Hunter",
        "element": "Metal",
        "equippable": "",
        "swf": "class-symone.swf",
        "savable": 0,
        "armorId": 9800461,
        "weaponId": 9800460
    },
    {
        "id": 116,
        "name": "Ancient Exosuit",
        "element": "Energy",
        "equippable": "Sword,Mace,Dagger,Axe,Ring,Necklace,Staff,Belt,Earring,Bracer,Pet,Cape,Wings,Helmet,Armor,Wand,Scythe,Trinket,Artifact",
        "swf": "class-playerExoSuit.swf",
        "savable": 14441,
        "armorId": 9800463,
        "weaponId": 9800462
    },
    {
        "id": 117,
        "name": "x",
        "element": "Darkness",
        "equippable": "Sword,Mace,Dagger,Axe,Ring,Necklace,Staff,Belt,Earring,Bracer,Pet,Cape,Wings,Helmet,Armor,Wand,Scythe,Trinket,Artifact",
        "swf": "x",
        "savable": 0,
        "armorId": 9800469,
        "weaponId": 9800468
    },
    {
        "id": 118,
        "name": "Archivist",
        "element": "Good",
        "equippable": "Sword,Mace,Dagger,Axe,Ring,Necklace,Staff,Belt,Earring,Bracer,Pet,Cape,Wings,Helmet,Armor,Wand,Scythe,Trinket,Artifact",
        "swf": "class-archivist-r10.swf",
        "savable": 14969,
        "armorId": 9800471,
        "weaponId": 9800470
    },
    {
        "id": 119,
        "name": "Danyel",
        "element": "Wind",
        "equippable": "",
        "swf": "class-danyel-r1.swf",
        "savable": 0,
        "armorId": 9800477,
        "weaponId": 9800476
    },
    {
        "id": 120,
        "name": "Fleshweaver",
        "element": "Bacon",
        "equippable": "Sword,Mace,Dagger,Axe,Ring,Necklace,Staff,Belt,Earring,Bracer,Pet,Helmet,Cape,Wings,Helmet,Armor,Wand,Scythe,Trinket,Artifact",
        "swf": "class-aprilfools.swf",
        "savable": 0,
        "armorId": 9800481,
        "weaponId": 9800480
    },
    {
        "id": 121,
        "name": "Caitiff",
        "element": "Evil",
        "equippable": "",
        "swf": "class-caitiff-r1.swf",
        "savable": 0,
        "armorId": 9800485,
        "weaponId": 9800484
    },
    {
        "id": 122,
        "name": "|",
        "element": "???",
        "equippable": "Sword,Mace,Dagger,Axe,Ring,Necklace,Staff,Belt,Earring,Bracer,Cape,Wings,Helmet,Armor,Wand,Scythe,Trinket,Artifact",
        "swf": "class-1d.swf",
        "savable": 1,
        "armorId": 9800489,
        "weaponId": 9800488
    },
    {
        "id": 123,
        "name": "Baby Dragon",
        "element": "None",
        "equippable": "",
        "swf": "class-DragonWarBaby-r1.swf ",
        "savable": 0,
        "armorId": 9800493,
        "weaponId": 9800492
    },
    {
        "id": 124,
        "name": "Retro Necromancer",
        "element": "Darkness",
        "equippable": "Sword,Mace,Dagger,Axe,Ring,Necklace,Staff,Belt,Earring,Bracer,Pet,Cape,Wings,Helmet,Armor,Wand,Scythe,Trinket,Artifact",
        "swf": "class-necromancerold-r5.swf",
        "savable": 2,
        "armorId": 9800497,
        "weaponId": 9800496
    },
    {
        "id": 125,
        "name": "Paladin",
        "element": "Metal",
        "equippable": "Sword,Mace,Dagger,Axe,Ring,Necklace,Staff,Belt,Earring,Bracer,Pet,Cape,Wings,Helmet,Armor,Wand,Scythe,Trinket,Artifact",
        "swf": "class-PallyRevamp2023.swf?ver=2",
        "savable": 2,
        "armorId": 9800501,
        "weaponId": 9800500
    },
    {
        "id": 126,
        "name": "Warrior",
        "element": "Metal",
        "equippable": "Sword,Mace,Dagger,Axe,Ring,Necklace,Staff,Belt,Earring,Bracer,Pet,Cape,Wings,Helmet,Armor,Wand,Scythe,Trinket,Artifact",
        "swf": "class-2016warrior-r3.swf?ver=1",
        "savable": 2,
        "armorId": 9800505,
        "weaponId": 9800504
    },
    {
        "id": 127,
        "name": "Mage",
        "element": "Nature",
        "equippable": "Sword,Mace,Dagger,Axe,Ring,Necklace,Staff,Belt,Earring,Bracer,Pet,Helmet,Cape,Wings,Helmet,Armor,Wand,Scythe,Trinket,Artifact",
        "swf": "class-2016mage-r3.swf?ver=1 ",
        "savable": 2,
        "armorId": 9800509,
        "weaponId": 9800508
    },
    {
        "id": 128,
        "name": "Rogue",
        "element": "Metal",
        "equippable": "Sword,Mace,Dagger,Axe,Ring,Necklace,Staff,Belt,Earring,Bracer,Pet,Cape,Wings,Helmet,Armor,Wand,Scythe,Trinket,Artifact",
        "swf": "class-2016rogue-r5.swf?ver=2",
        "savable": 2,
        "armorId": 9800513,
        "weaponId": 9800512
    },
    {
        "id": 129,
        "name": "Shadow Warrior",
        "element": "Metal",
        "equippable": "Sword,Mace,Dagger,Axe,Ring,Necklace,Staff,Belt,Earring,Bracer,Pet,Cape,Wings,Helmet,Armor,Wand,Scythe,Trinket,Artifact",
        "swf": "class-shadowwarrior.swf?ver=2",
        "savable": 16024,
        "armorId": 9800515,
        "weaponId": 9800514
    },
    {
        "id": 130,
        "name": "Shadow Mage",
        "element": "Nature",
        "equippable": "Sword,Mace,Dagger,Axe,Ring,Necklace,Staff,Belt,Earring,Bracer,Pet,Cape,Wings,Helmet,Armor,Wand,Scythe,Trinket,Artifact",
        "swf": "class-shadowmage.swf?ver=2",
        "savable": 16023,
        "armorId": 9800517,
        "weaponId": 9800516
    },
    {
        "id": 131,
        "name": "Shadow Rogue",
        "element": "Metal",
        "equippable": "Sword,Mace,Dagger,Axe,Ring,Necklace,Staff,Belt,Earring,Bracer,Pet,Cape,Wings,Helmet,Armor,Wand,Scythe,Trinket,Artifact",
        "swf": "class-shadowrogue-r3.swf",
        "savable": 16022,
        "armorId": 9800519,
        "weaponId": 9800518
    },
    {
        "id": 132,
        "name": "Paladin of Light",
        "element": "Light",
        "equippable": "",
        "swf": "class-Artix-bk3.swf",
        "savable": 0,
        "armorId": 9800529,
        "weaponId": 9800528
    },
    {
        "id": 134,
        "name": "Boxcat",
        "element": "Metal",
        "equippable": "Sword,Mace,Dagger,Axe,Ring,Necklace,Staff,Belt,Earring,Bracer,Pet,Cape,Wings,Helmet,Armor,Wand,Scythe,Trinket,Artifact",
        "swf": "class-verlyRangerTest.swf",
        "savable": 2,
        "armorId": 9800537,
        "weaponId": 9800536
    },
    {
        "id": 135,
        "name": "Big Cheese",
        "element": "Nature",
        "equippable": "",
        "swf": "class-sanrobin.swf",
        "savable": 0,
        "armorId": 9800541,
        "weaponId": 9800540
    },
    {
        "id": 136,
        "name": "VIP",
        "element": "None",
        "equippable": "",
        "swf": "class-suit.swf",
        "savable": 0,
        "armorId": 9800545,
        "weaponId": 9800544
    },
    {
        "id": 137,
        "name": "VIP",
        "element": "None",
        "equippable": "",
        "swf": "class-dress.swf",
        "savable": 0,
        "armorId": 9800549,
        "weaponId": 9800548
    },
    {
        "id": 138,
        "name": "Faust",
        "element": "None",
        "equippable": "",
        "swf": "class-faust.swf",
        "savable": 0,
        "armorId": 9800553,
        "weaponId": 9800552
    },
    {
        "id": 139,
        "name": "Necro Paragon",
        "element": "Darkness",
        "equippable": "Sword,Mace,Dagger,Axe,Ring,Necklace,Staff,Belt,Earring,Bracer,Pet,Cape,Wings,Helmet,Armor,Wand,Scythe,Trinket,Artifact",
        "swf": "class-necroparagon-r8.swf",
        "savable": 17776,
        "armorId": 9800555,
        "weaponId": 9800554
    },
    {
        "id": 141,
        "name": "Ascendant",
        "element": "Ice",
        "equippable": "Sword,Mace,Dagger,Axe,Ring,Necklace,Staff,Belt,Earring,Bracer,Pet,Cape,Wings,Helmet,Armor,Wand,Scythe,Trinket,Artifact",
        "swf": "class-ascendant-NEW.swf",
        "savable": 2,
        "armorId": 9800565,
        "weaponId": 9800564
    },
    {
        "id": 142,
        "name": "Riftwalker",
        "element": "Ice",
        "equippable": "Sword,Mace,Dagger,Axe,Ring,Necklace,Staff,Belt,Earring,Bracer,Pet,Cape,Wings,Helmet,Armor,Wand,Scythe,Trinket,Artifact",
        "swf": "CLASS-Riftwalker-NEW.swf",
        "savable": 2,
        "armorId": 9800569,
        "weaponId": 9800568
    },
    {
        "id": 143,
        "name": "Cryptic",
        "element": "Ice",
        "equippable": "Sword,Mace,Dagger,Axe,Ring,Necklace,Staff,Belt,Earring,Bracer,Pet,Cape,Wings,Helmet,Armor,Wand,Scythe,Trinket,Artifact",
        "swf": "class-cryptic-NEW.swf",
        "savable": 2,
        "armorId": 9800573,
        "weaponId": 9800572
    },
    {
        "id": 144,
        "name": "Ninja",
        "element": "Darkness",
        "equippable": "Sword,Mace,Dagger,Axe,Ring,Necklace,Staff,Belt,Earring,Bracer,Pet,Cape,Wings,Helmet,Armor,Wand,Scythe,Trinket,Artifact",
        "swf": "class-NinjaRevamp2023.swf?ver=3",
        "savable": 2,
        "armorId": 9800577,
        "weaponId": 9800576
    },
    {
        "id": 145,
        "name": "Ninja",
        "element": "Darkness",
        "equippable": "Sword,Mace,Dagger,Axe,Ring,Necklace,Staff,Belt,Earring,Bracer,Pet,Cape,Wings,Helmet,Armor,Wand,Scythe,Trinket,Artifact",
        "swf": "class-NinjaRevamp2023.swf?ver=3",
        "savable": 2,
        "armorId": 9800581,
        "weaponId": 9800580
    },
    {
        "id": 146,
        "name": "SoulWeaver",
        "element": "Metal",
        "equippable": "Sword,Mace,Dagger,Axe,Ring,Necklace,Staff,Belt,Earring,Bracer,Pet,Cape,Wings,Helmet,Armor,Wand,Scythe,Trinket,Artifact",
        "swf": "class-soul2024-r1.swf",
        "savable": 2,
        "armorId": 9800585,
        "weaponId": 9800584
    },
    {
        "id": 147,
        "name": "Dreaming Togslayer",
        "element": "Ice",
        "equippable": "Sword,Mace,Dagger,Axe,Ring,Necklace,Staff,Belt,Earring,Bracer,Pet,Cape,Wings,Helmet,Armor,Wand,Scythe,Trinket,Artifact",
        "swf": "class-Togslayernew.swf?ver=1",
        "savable": 18055,
        "armorId": 9800587,
        "weaponId": 9800586
    },
    {
        "id": 149,
        "name": "Sleepy Hero",
        "element": "None",
        "equippable": "",
        "swf": "class-pajamas.swf",
        "savable": 0,
        "armorId": 9800597,
        "weaponId": 9800596
    },
    {
        "id": 150,
        "name": "Sam",
        "element": "Silver",
        "equippable": "",
        "swf": "class-Sam.swf",
        "savable": 0,
        "armorId": 9800601,
        "weaponId": 9800600
    },
    {
        "id": 153,
        "name": "Apprentice Hero",
        "element": "Nature",
        "equippable": "",
        "swf": "class-falwynn-r1.swf",
        "savable": 0,
        "armorId": 9800613,
        "weaponId": 9800612
    },
    {
        "id": 154,
        "name": "Student",
        "element": "Metal",
        "equippable": "Sword,Mace,Dagger,Axe,Ring,Necklace,Staff,Belt,Earring,Bracer,Pet,Cape,Wings,Helmet,Armor,Wand,Scythe,Trinket,Artifact",
        "swf": "class-school-r2.swf?ver=2",
        "savable": 20175,
        "armorId": 9800615,
        "weaponId": 9800614
    },
    {
        "id": 155,
        "name": "Chronomancer",
        "element": "Metal",
        "equippable": "Sword,Mace,Dagger,Axe,Ring,Necklace,Staff,Belt,Earring,Bracer,Pet,Cape,Wings,Helmet,Armor,Wand,Scythe,Trinket,Artifact",
        "swf": "class-chrono-new.swf",
        "savable": 2,
        "armorId": 9800621,
        "weaponId": 9800620
    },
    {
        "id": 156,
        "name": "Chronocorruptor",
        "element": "Ice",
        "equippable": "Sword,Mace,Dagger,Axe,Ring,Necklace,Staff,Belt,Earring,Bracer,Pet,Cape,Wings,Helmet,Armor,Wand,Scythe,Trinket,Artifact",
        "swf": "class-chaoschrono-new.swf",
        "savable": 2,
        "armorId": 9800625,
        "weaponId": 9800624
    },
    {
        "id": 157,
        "name": "ChronoZ",
        "element": "Ice",
        "equippable": "Sword,Mace,Dagger,Axe,Ring,Necklace,Staff,Belt,Earring,Bracer,Pet,Cape,Wings,Helmet,Armor,Wand,Scythe,Trinket,Artifact",
        "swf": "class-ChronoZ-reforged.swf?ver=1",
        "savable": 2,
        "armorId": 9800629,
        "weaponId": 9800628
    },
    {
        "id": 158,
        "name": "TimeKiller",
        "element": "Metal",
        "equippable": "Sword,Mace,Dagger,Axe,Ring,Necklace,Staff,Belt,Earring,Bracer,Pet,Cape,Wings,Helmet,Armor,Wand,Scythe,Trinket,Artifact",
        "swf": "class-timekiller-reforged.swf",
        "savable": 2,
        "armorId": 9800633,
        "weaponId": 9800632
    },
    {
        "id": 159,
        "name": "Avatar of Time",
        "element": "???",
        "equippable": "Sword,Mace,Dagger,Axe,Ring,Necklace,Staff,Belt,Earring,Bracer,Pet,Cape,Wings,Helmet,Armor,Wand,Scythe,Trinket,Artifact",
        "swf": "class-timeavatar-reforged.swf",
        "savable": 2,
        "armorId": 9800637,
        "weaponId": 9800636
    },
    {
        "id": 160,
        "name": "Archivist",
        "element": "Good",
        "equippable": "Sword,Mace,Dagger,Axe,Ring,Necklace,Staff,Belt,Earring,Bracer,Pet,Cape,Wings,Helmet,Armor,Wand,Scythe,Trinket,Artifact",
        "swf": "class-archivist-reforged-r1.swf?ver=1",
        "savable": 2,
        "armorId": 9800641,
        "weaponId": 9800640
    },
    {
        "id": 161,
        "name": "DragonRider",
        "element": "Fire",
        "equippable": "",
        "swf": "class-odgnerider.swf ",
        "savable": 0,
        "armorId": 9800645,
        "weaponId": 9800644
    },
    {
        "id": 162,
        "name": "ShadowWalker of Time",
        "element": "???",
        "equippable": "Sword,Mace,Dagger,Axe,Ring,Necklace,Staff,Belt,Earring,Bracer,Pet,Cape,Wings,Helmet,Armor,Wand,Scythe,Trinket,Artifact",
        "swf": "class-swotreforged.swf",
        "savable": 2,
        "armorId": 9800649,
        "weaponId": 9800648
    },
    {
        "id": 163,
        "name": "Snugglemech",
        "element": "Metal",
        "equippable": "Sword,Mace,Dagger,Axe,Ring,Necklace,Staff,Belt,Earring,Bracer,Pet,Cape,Wings,Armor,Wand,Scythe,Trinket,Artifact",
        "swf": "class-snugglemech.swf?ver=1",
        "savable": 0,
        "armorId": 9800653,
        "weaponId": 9800652
    }
]